{
    "id": 8,
    "title": "الحكم بما أنزل الله ",
    "description": "الحكم بما أنزل الله   ",
    "search": " بحث عن موضوع في كتاب الحكم بما أنزل الله ",
    "type": "المادة",
    "author": "  الشيخ ياسر برهامي",
    "publisher": "د . حالد منصور",
    "section": "قضايا فكرية ",
    "year": 2000,
    "audio_count": 8,
    "audio_type": "mp4",
    "sort": "id",
    "download": "",
    "url": "https://www.youtube.com/embed",
    "image": "https://www.noor-book.com/publice/covers_cache_webp/17/d/e/f/780c95ede6def701676bfba3127e55b0.jpg.webp",
    "data": [
        {
            "id": 1,
            "name": "قضية الحكم بما انزل الله وما يتعلق بها .. ( 1 ) .. لفضيلة الشيخ خالد منصور",
            "url": "f5Q4srPTpaY"
        },
        {
            "id": 2,
            "name": "قضية الحكم بما انزل الله وما يتعلق بها .. ( 2 ) .. لفضيلة الشيخ خالد منصور",
            "url": "0d0PXhYWW3g"
        },
        {
            "id": 3,
            "name": "قضية الحكم بما انزل الله وما يتعلق بها .. ( 3 ) .. لفضيلة الشيخ خالد منصور",
            "url": "stQCKPZJBQU"
        },
        {
            "id": 4,
            "name": "قضية الحكم بما انزل الله وما يتعلق بها .. ( 4 ) .. لفضيلة الشيخ خالد منصور",
            "url": "RKy7NMLeiFs"
        },
        {
            "id": 5,
            "name": "قضية الحكم بما انزل الله وما يتعلق بها .. ( 6 ) .. لفضيلة الشيخ خالد منصور",
            "url": "Neq3s1IbZjU"
        },
        {
            "id": 6,
            "name": "قضية الحكم بما انزل الله وما يتعلق بها .. ( 5 ) .. لفضيلة الشيخ خالد منصور",
            "url": "vqTas4KmjZE"
        },
        {
            "id": 7,
            "name": "قضية الحكم بما انزل الله وما يتعلق بها .. ( 7 ) .. لفضيلة الشيخ خالد منصور",
            "url": "DlYpIUfcII0"
        },
        {
            "id": 8,
            "name": "قضية الحكم بما انزل الله وما يتعلق بها .. ( 8 ) .. لفضيلة الشيخ خالد منصور",
            "url": "AKmSIJtd-2k"
        }
    ]
}